ParticleInteractionSimulationSystem/__init__.py
ParticleInteractionSimulationSystem/main.py
ParticleInteractionSimulationSystem-0.3.dist-info/METADATA
ParticleInteractionSimulationSystem-0.3.dist-info/WHEEL
ParticleInteractionSimulationSystem-0.3.dist-info/top_level.txt
ParticleInteractionSimulationSystem-0.3.dist-info/RECORD
