Metadata-Version: 2.1
Name: ParticleInteractionSimulationSystem
Version: 0.3
Summary: A Lightweight Pygame Particle System
Author: SirBilby
License: MIT
Requires-Dist: pygame
